{
  "audioWordlistId": 0,
  "censorCharacter": "*",
  "censorFixedLength": 0,
  "collectStats": true,
  "contextMenu": true,
  "customAudioSites": null,
  "darkMode": true,
  "defaultSubstitution": "censored",
  "defaultWordMatchMethod": 0,
  "defaultWordRepeat": 0,
  "defaultWordSeparators": 0,
  "domains": {},
  "enabledDomainsOnly": false,
  "enabledFramesOnly": false,
  "fillerAudio": "",
  "fillerAudioCustom": {},
  "filterMethod": 1,
  "filterWordList": false,
  "iWordAllowlist": [],
  "language": "en",
  "loggingLevel": 2,
  "muteAudio": false,
  "muteAudioOnly": false,
  "muteCueRequireShowing": false,
  "muteMethod": 0,
  "password": null,
  "preserveCase": true,
  "preserveFirst": true,
  "preserveLast": false,
  "showCounter": true,
  "showSubtitles": 0,
  "showSummary": true,
  "showUpdateNotification": false,
  "substitutionMark": false,
  "syncLargeKeys": true,
  "unmuteDelay": 0,
  "wordAllowlist": [],
  "wordSubSeparator": ";;",
  "wordlistId": 1,
  "wordlists": [
    "Wordlist 1",
    "Wordlist 2",
    "Wordlist 3",
    "Wordlist 4",
    "Wordlist 5",
    "Wordlist 6"
  ],
  "wordlistsEnabled": false,
  "words": {"8 củ": {"case": 0,"lists": [3],"matchMethod": 0,"repeat": 0,"separators": 0,"sub": "8 triệuֹֹ"}
,"9 củ": {"case": 0,"lists": [3],"matchMethod": 0,"repeat": 0,"separators": 0,"sub": "9 triệuֹֹ"}
,"10 củ": {"case": 0,"lists": [3],"matchMethod": 0,"repeat": 0,"separators": 0,"sub": "10 triệuֹֹ"}
,"11 củ": {"case": 0,"lists": [3],"matchMethod": 0,"repeat": 0,"separators": 0,"sub": "11 triệuֹֹ"}
,"12 củ": {"case": 0,"lists": [3],"matchMethod": 0,"repeat": 0,"separators": 0,"sub": "12 triệuֹֹ"}
,"13 củ": {"case": 0,"lists": [3],"matchMethod": 0,"repeat": 0,"separators": 0,"sub": "13 triệuֹֹ"}
,"14 củ": {"case": 0,"lists": [3],"matchMethod": 0,"repeat": 0,"separators": 0,"sub": "14 triệuֹֹ"}
,"15 củ": {"case": 0,"lists": [3],"matchMethod": 0,"repeat": 0,"separators": 0,"sub": "15 triệuֹֹ"}
,"chính quyền nhân dân": {"case": 1,"lists": [2],"matchMethod": 0,"repeat": 0,"separators": 0,"sub": "Đảng Cộng Sảnֹֹ"}
,"chống nhà nước cộng hòa xhcn việt nam": {"case": 0,"lists": [2],"matchMethod": 0,"repeat": 0,"separators": 0,"sub": "chống chính quyềnֹֹ"}
,"chống nhà nước cộng hòa xã hội chủ nghĩa việt nam": {"case": 0,"lists": [2],"matchMethod": 0,"repeat": 0,"separators": 0,"sub": "chống chính quyềnֹֹ"}
,"chống phá nhà nước cộng hòa xã hội chủ nghĩa việt nam": {"case": 0,"lists": [2],"matchMethod": 0,"repeat": 0,"separators": 0,"sub": "chống chính quyềnֹֹ"}
,"chống phá đảng, nhà nước": {"case": 1,"lists": [2],"matchMethod": 0,"repeat": 0,"separators": 0,"sub": "chống Đảng Cộng Sản, chính quyềnֹֹ"}
,"chống phá đất nước": {"case": 0,"lists": [2],"matchMethod": 0,"repeat": 0,"separators": 0,"sub": "phê phán chính quyềnֹ"}
,"giải phóng hoàn toàn miền nam": {"case": 1,"lists": [2],"matchMethod": 0,"repeat": 0,"separators": 0,"sub": "cưỡng chiếm Miền Namֹֹ"}
,"giải phóng miền nam": {"case": 1,"lists": [2],"matchMethod": 0,"repeat": 0,"separators": 0,"sub": "cưỡng chiếm Miền Namֹֹ"}
,"hỗ trợ tài chính": {"case": 0,"lists": [2],"matchMethod": 0,"repeat": 0,"separators": 0,"sub": "cho vay nặng lãi⚠ֹ"}
,"khủng bố việt tân": {"case": 1,"lists": [2],"matchMethod": 0,"repeat": 0,"separators": 0,"sub": "Việt Tânֹֹ"}
,"tuyên truyền": {"case": 0,"lists": [2],"matchMethod": 0,"repeat": 0,"separators": 0,"sub": "tuyênֹ truyền⚠ֹ"}
,"-Cap nhat danh sach -Create day 2025/01/12ֹ": {"case": 0,"lists": [],"matchMethod": 0,"repeat": 0,"separators": 0,"sub": "https://raw.githubusercontent.com/stoism/sources/main/textreplace/AdvancedProfanityFilterList.jsonֹ"}},
  "youTubeAutoMatchCensored": true,
  "youTubeAutoSubsMax": 0,
  "youTubeAutoSubsMin": 0
}